{ "posts": [{
    "pseudonym": "The Creator",
    "topic": "Welcome",
    "body": "Welcome to the hellaRad blog, I've never seen a blog before but here I am making one.",
    "image": "image.jpg",
    "category": "Psychedelic"
    }, {
    "pseudonym": "Bender",
    "topic": "Bending",
    "body": "It sure is great",
    "image": "http://clipartsign.com/upload/2016/02/07/rocket-clip-art-free-2.jpg",
    "category": "Taco Tuesday"
  }, {
    "pseudonym": "Lvl420 WeedWizard",
    "topic": "...dude... I..",
    "body": "Day 789,387 still exist, I think... Dude what if nobody exists?",
    "image": "http://www.clipartbest.com/cliparts/9cR/gqx/9cRgqxKMi.png",
    "category": "Memes"
  }],

  "categories": [{
    "name": "Psychedelic"
  }, {
    "name": "Memes"
  }, {
    "name": "Taco Tuesday"
  }]
}
